LICENSE
MANIFEST.in
README.md
requirements.txt
setup.cfg
setup.py
sofes/__init__.py
sofes/dataset.py
sofes/mutate_labels.py
sofes/mutated_validation.py
sofes/proto_initializer.py
sofes/sofes.py
sofes.egg-info/PKG-INFO
sofes.egg-info/SOURCES.txt
sofes.egg-info/dependency_links.txt
sofes.egg-info/not-zip-safe
sofes.egg-info/requires.txt
sofes.egg-info/top_level.txt
tests/test_sofes.py