Metadata-Version: 2.1
Name: sofes
Version: 0.0.1
Summary: A python package for prototype-based soft feature selection
Home-page: https://github.com/naotoo1/sofes
Author: Nana Abeka Otoo
Author-email: abekaotoo@gmail.com
License: MIT license
Keywords: sofes
Classifier: Intended Audience :: Developers
Classifier: License :: OSI Approved :: MIT License
Classifier: Natural Language :: English
Classifier: Development Status :: 4 - Beta
Classifier: Intended Audience :: Developers
Classifier: Intended Audience :: Education
Classifier: Intended Audience :: Science/Research
Classifier: Topic :: Scientific/Engineering :: Artificial Intelligence
Classifier: Topic :: Software Development :: Libraries
Classifier: Topic :: Software Development :: Libraries :: Python Modules
Classifier: License :: OSI Approved :: MIT License
Classifier: Operating System :: OS Independent
Classifier: Programming Language :: Python :: 3.6
Classifier: Programming Language :: Python :: 3.7
Requires-Python: >=3.6
License-File: LICENSE
Requires-Dist: dataclasses==0.6
Requires-Dist: imbalanced-learn==0.8.1
Requires-Dist: imblearn==0.0
Requires-Dist: matplotlib==2.0.0
Requires-Dist: numpy
Requires-Dist: pandas==0.24.0
Requires-Dist: scikit-learn==0.24.2
Requires-Dist: scipy==1.5.4
Requires-Dist: sklearn-lvq==1.1.1
